[{"yt_vid": "dD96V34j3Gk", "num_comments": 1, "title": "In honor of a curfew taking effect where I can now literally be arrested for walking on the street pst 10pm. The most applicable song I could think of, The Cigarettes - Stay Inside (1979, Mod)", "id": "34882k", "over_18": false, "subreddit": "punk", "score": 12, "created_utc": 1430272755}, {"yt_vid": "vJck3zfrczg", "num_comments": 0, "title": "Anti-Flag - No Borders, No Nations (Live)", "id": "31xv7g", "over_18": false, "subreddit": "punk", "score": 3, "created_utc": 1428539320}, {"yt_vid": "MrTYy8lnqKM", "num_comments": 0, "title": "INDK-Sunday Bombs [hardcore/CRS]", "id": "31gxhr", "over_18": false, "subreddit": "punk", "score": 5, "created_utc": 1428191409}, {"yt_vid": "-qIQ5zOuf2c", "num_comments": 1, "title": "The Hives - \"What's That Spell... Go To Hell!\"", "id": "31tble", "over_18": false, "subreddit": "punk", "score": 7, "created_utc": 1428452293}, {"yt_vid": "cfzhq1CjJG0", "num_comments": 4, "title": "Minutemen - History Lesson - Happy Birthday to D. Boon", "id": "317x1v", "over_18": false, "subreddit": "punk", "score": 93, "created_utc": 1427999705}, {"yt_vid": "TeJPDNcsC0Y", "num_comments": 0, "title": "Fuck You!", "id": "336ewe", "over_18": false, "subreddit": "punk", "score": 0, "created_utc": 1429487681}, {"yt_vid": "L7EkuGCfkYI", "num_comments": 0, "title": "The Faction-Skate and Destroy", "id": "329sze", "over_18": false, "subreddit": "punk", "score": 4, "created_utc": 1428789359}, {"yt_vid": "qzK2ydMjIUQ", "num_comments": 0, "title": "The Flesheaters - Eyes Without A Face", "id": "3102hr", "over_18": false, "subreddit": "punk", "score": 1, "created_utc": 1427852988}, {"yt_vid": "EVnuuBqBv9Q", "num_comments": 0, "title": "Sweepyheads - I'll Just Go Fuck Myself (2015) DIY Live Vid", "id": "33xsnd", "over_18": false, "subreddit": "punk", "score": 2, "created_utc": 1430070221}, {"yt_vid": "rRzApuTmyLs", "num_comments": 0, "title": "Face of Change - Free Will (1990)(Japan)(They sound like a Japanese 7 Seconds)", "id": "31zfg0", "over_18": false, "subreddit": "punk", "score": 2, "created_utc": 1428575547}, {"yt_vid": "gIiaPuEYuq0", "num_comments": 0, "title": "Del Sesto (ventura county anarcho punk)- Never crust a trustie", "id": "32waz1", "over_18": false, "subreddit": "punk", "score": 3, "created_utc": 1429251860}, {"yt_vid": "UdZvTNqih4I", "num_comments": 0, "title": "The Huntingtons - I Wanna Be A Ramone", "id": "318cs1", "over_18": false, "subreddit": "punk", "score": 5, "created_utc": 1428006358}, {"yt_vid": "CZ77EXS9WrE", "num_comments": 0, "title": "Sterile Hermaphrodite - The Moon (punk,metal,grunge)", "id": "33evzt", "over_18": false, "subreddit": "punk", "score": 2, "created_utc": 1429658824}, {"yt_vid": "0t-d9CUXWNU", "num_comments": 0, "title": "Screaming Noise - Fuck the Hero.", "id": "33pvi2", "over_18": false, "subreddit": "punk", "score": 5, "created_utc": 1429887996}, {"yt_vid": "sVLf7YjkcQg", "num_comments": 0, "title": "GG Allin &amp; The Scumfucs - I Don't Give A Shit", "id": "333bha", "over_18": false, "subreddit": "punk", "score": 0, "created_utc": 1429412476}, {"yt_vid": "TOUzgGNN1F4", "num_comments": 1, "title": "Guttermouth Heated Tossed Salad", "id": "326pqu", "over_18": false, "subreddit": "punk", "score": 0, "created_utc": 1428715422}, {"yt_vid": "mOf6w59jz_g", "num_comments": 0, "title": "Great new DC hardcore", "id": "313nhh", "over_18": false, "subreddit": "punk", "score": 0, "created_utc": 1427917828}, {"yt_vid": "jUUlUtUPO98", "num_comments": 1, "title": "Big Fat Zucchini - Steven and the Stevens", "id": "327hc4", "over_18": false, "subreddit": "punk", "score": 5, "created_utc": 1428733368}, {"yt_vid": "L32aagA-2Os", "num_comments": 0, "title": "NOFX - Linoleum Cover HD", "id": "344xnf", "over_18": false, "subreddit": "punk", "score": 0, "created_utc": 1430214242}, {"yt_vid": "TPKQSQSVVos", "num_comments": 0, "title": "Use to listen to these guys so much back in the day. Dinosaurs will die - NoFx", "id": "32j3p7", "over_18": false, "subreddit": "punk", "score": 0, "created_utc": 1428987377}, {"yt_vid": "ipafT1Rcsf0", "num_comments": 0, "title": "New We Are The Union - Call In Dead. Coming out on Paper + Plastick.", "id": "32q418", "over_18": false, "subreddit": "punk", "score": 2, "created_utc": 1429129681}, {"yt_vid": "UGN1TUt2lyc", "num_comments": 19, "title": "Fat Wreck USA Tour Announced", "id": "345mfj", "over_18": false, "subreddit": "punk", "score": 9, "created_utc": 1430230768}, {"yt_vid": "9X-r8zP-rnk", "num_comments": 2, "title": "The Restarts - Frustration (Favorite Band)", "id": "31yn2o", "over_18": false, "subreddit": "punk", "score": 14, "created_utc": 1428553283}, {"yt_vid": "_1Nd8UXXijQ", "num_comments": 0, "title": "The Bronx - Too Many Devils", "id": "32pf18", "over_18": false, "subreddit": "punk", "score": 1, "created_utc": 1429118675}, {"yt_vid": "gioPY2HoptE", "num_comments": 0, "title": "Poison Idea- Me and JD", "id": "33pzqp", "over_18": false, "subreddit": "punk", "score": 5, "created_utc": 1429889916}, {"yt_vid": "ruJPXy_D3UE", "num_comments": 0, "title": "Desaparecidos - City On The Hill", "id": "33hhqn", "over_18": false, "subreddit": "punk", "score": 1, "created_utc": 1429717560}, {"yt_vid": "EOzxvLBlmcU", "num_comments": 6, "title": "Groovie Ghoulies - I Wanna Have Fun With You", "id": "3257v4", "over_18": false, "subreddit": "punk", "score": 37, "created_utc": 1428688915}, {"yt_vid": "LlnICnPQ9ag", "num_comments": 13, "title": "Menzingers sophomore album Chamberlain Waits is 5 years old today.", "id": "32idjd", "over_18": false, "subreddit": "punk", "score": 62, "created_utc": 1428973563}, {"yt_vid": "v2H8FtlrzCI", "num_comments": 4, "title": "Die Toten Hosen - Pushed Again (1998) [English Vocals]", "id": "324mlx", "over_18": false, "subreddit": "punk", "score": 12, "created_utc": 1428679287}, {"yt_vid": "WNqqByKiiAA", "num_comments": 0, "title": "Talco - Bella Ciao", "id": "341rsi", "over_18": false, "subreddit": "punk", "score": 6, "created_utc": 1430154237}, {"yt_vid": "iM-0hUHaq0k", "num_comments": 8, "title": "Okay so which one of you guys is the Bad Religion Boy @ 1:01 ?", "id": "32zv8j", "over_18": false, "subreddit": "punk", "score": 34, "created_utc": 1429327349}, {"yt_vid": "XIHEwr29XmE", "num_comments": 0, "title": "Clean Jeans - SPORTS [Garage Punk] [2014]", "id": "31z0be", "over_18": false, "subreddit": "punk", "score": 1, "created_utc": 1428562236}, {"yt_vid": "wt63EoEdSdY", "num_comments": 0, "title": "Zouo - Bloody Master", "id": "312hfb", "over_18": false, "subreddit": "punk", "score": 6, "created_utc": 1427903125}, {"yt_vid": "EPUuu0i2U6k", "num_comments": 0, "title": "Anti-Flag - Sky Is Falling (Brand New Single)", "id": "349saj", "over_18": false, "subreddit": "punk", "score": 0, "created_utc": 1430312368}, {"yt_vid": "lN4zSZboL58", "num_comments": 3, "title": "Sourpuss \u2013 Dr Faustus [punk/riotgrrl] (1995) A 17 year old Brody Dalle (Distillers, Spinerette) and rare live footage of her first band in Melbourne, Australia.", "id": "343ktq", "over_18": false, "subreddit": "punk", "score": 4, "created_utc": 1430182674}, {"yt_vid": "2NEZRPzNF2Q", "num_comments": 0, "title": "Nozin' Around (1982) Punk show for young adults by young adults", "id": "31wsc6", "over_18": false, "subreddit": "punk", "score": 1, "created_utc": 1428522068}, {"yt_vid": "QgGszKLBmP8", "num_comments": 7, "title": "Bunchofuckingoofs - In Dog We Trust [Toronto, ON, Hardcore, 1992]", "id": "33qdzk", "over_18": false, "subreddit": "punk", "score": 12, "created_utc": 1429896442}, {"yt_vid": "3ou_ohqC-4c", "num_comments": 4, "title": "This sucks. r.i.p. Ceremony. 2 mediocre albums in a row and then this...", "id": "33ts9h", "over_18": false, "subreddit": "punk", "score": 0, "created_utc": 1429976544}, {"yt_vid": "IX31tvT2Br8", "num_comments": 4, "title": "The Smith Street Band - \"I Don't Wanna Die Anymore\" (live at Little Elephant)", "id": "33m9hb", "over_18": false, "subreddit": "punk", "score": 22, "created_utc": 1429811427}, {"yt_vid": "N8KAAgKcfeA", "num_comments": 0, "title": "Plague Vendor - Breakdance On Broken Glass", "id": "33us7n", "over_18": false, "subreddit": "punk", "score": 7, "created_utc": 1429994925}, {"yt_vid": "w8aIKBr4Hg8", "num_comments": 5, "title": "Be Your Own Pet - Fill My Pill. Jemina's my favorite female punk singer.", "id": "31bvcf", "over_18": false, "subreddit": "punk", "score": 36, "created_utc": 1428081542}, {"yt_vid": "JSzM2aVD0X8", "num_comments": 5, "title": "The Bennies - My Bike (Melbourne Party Punk, Australia)", "id": "3379jp", "over_18": false, "subreddit": "punk", "score": 14, "created_utc": 1429505282}, {"yt_vid": "x7YHHK9WReY", "num_comments": 2, "title": "Joe Strummer &amp; The Mescaleros - Coma Girl", "id": "347z6s", "over_18": false, "subreddit": "punk", "score": 69, "created_utc": 1430268588}, {"yt_vid": "6MAQxOBiD6A", "num_comments": 0, "title": "LA FEMME - SUR LA PLANCHE (France 2013)", "id": "34galg", "over_18": false, "subreddit": "punk", "score": 2, "created_utc": 1430432091}, {"yt_vid": "pXLmXvLE3h8", "num_comments": 1, "title": "Nina Hagen - 1983 Berlin interview &amp; clips", "id": "346cdw", "over_18": false, "subreddit": "punk", "score": 2, "created_utc": 1430242296}, {"yt_vid": "xFYXP19e5KM", "num_comments": 0, "title": "Turbonegro - Fuck The World", "id": "32toj5", "over_18": false, "subreddit": "punk", "score": 1, "created_utc": 1429203745}, {"yt_vid": "FxvC-pwqdcw", "num_comments": 2, "title": "Rancid - I Wanna Riot (Ska Version - Feat: Stubborn All Stars) [Underrated Rancid song, and politically relevant, so we can let it slide]", "id": "34897d", "over_18": false, "subreddit": "punk", "score": 0, "created_utc": 1430273283}, {"yt_vid": "XDheLViZbrk", "num_comments": 1, "title": "Suicidal Tendencies - Trip at the Brain", "id": "33iow6", "over_18": false, "subreddit": "punk", "score": 12, "created_utc": 1429736378}, {"yt_vid": "wqnvmlGeCKk", "num_comments": 0, "title": "Husker Du - 22. Diane 9/5/81 7th Street Entry", "id": "314kib", "over_18": false, "subreddit": "punk", "score": 1, "created_utc": 1427930371}, {"yt_vid": "QunPzFV41uk", "num_comments": 1, "title": "Dead Moon-It's O.K.", "id": "33zich", "over_18": false, "subreddit": "punk", "score": 6, "created_utc": 1430101433}, {"yt_vid": "kMRNiZuQVCE", "num_comments": 3, "title": "Rise Against - Tragedy + Time intro verse animation [OC]", "id": "32xqil", "over_18": false, "subreddit": "punk", "score": 2, "created_utc": 1429287218}, {"yt_vid": "YjQhZsADQ4g", "num_comments": 0, "title": "The Real Kids - \"Who Needs You\" - (Boston 1976)", "id": "315fi2", "over_18": false, "subreddit": "punk", "score": 10, "created_utc": 1427944589}, {"yt_vid": "nARoLYSyV0E", "num_comments": 0, "title": "Iron Reagan- Broken Bottles", "id": "347cdy", "over_18": false, "subreddit": "punk", "score": 4, "created_utc": 1430257619}, {"yt_vid": "0o2WsqUTypQ", "num_comments": 0, "title": "The Circle Jerks - The Slave (Germs Cover)", "id": "31mhui", "over_18": false, "subreddit": "punk", "score": 1, "created_utc": 1428326219}, {"yt_vid": "INSncTxr1w8", "num_comments": 0, "title": "BBC - Evidently... John Cooper Clarke", "id": "32t6do", "over_18": false, "subreddit": "punk", "score": 12, "created_utc": 1429195810}, {"yt_vid": "kp5c49sIx5E", "num_comments": 0, "title": "Warheads - Desperate - Svensk Punk", "id": "33s9fc", "over_18": false, "subreddit": "punk", "score": 1, "created_utc": 1429931635}, {"yt_vid": "TkLjV2kPeDE", "num_comments": 0, "title": "Edith Nylon - Waldorf, Power-Punk, 1979, France", "id": "348e2k", "over_18": false, "subreddit": "punk", "score": 1, "created_utc": 1430275656}, {"yt_vid": "q0B95FjppEs", "num_comments": 0, "title": "The Saints: 'This Perfect Day' Top of the Pops 1977", "id": "31baye", "over_18": false, "subreddit": "punk", "score": 1, "created_utc": 1428072475}, {"yt_vid": "NJia6TEVnwQ", "num_comments": 10, "title": "Alkaline Trio: I'm dying tomorrow (live) From Here to the Infirmary turns 14 years old today!", "id": "31btzi", "over_18": false, "subreddit": "punk", "score": 51, "created_utc": 1428080940}, {"yt_vid": "kLngKfzwVQ8", "num_comments": 8, "title": "Green Day with Tim Armstrong - Knowledge (Op Ivy) and Radio (Rancid)", "id": "32x07q", "over_18": false, "subreddit": "punk", "score": 19, "created_utc": 1429274045}, {"yt_vid": "Q2I-7fQPP5w", "num_comments": 2, "title": "T.S.O.L. - In My Head", "id": "334xdd", "over_18": false, "subreddit": "punk", "score": 33, "created_utc": 1429460060}, {"yt_vid": "TSHGJ89P3w8", "num_comments": 0, "title": "Cerebral Ballzy - Don't Tell Me What To Do", "id": "31oexa", "over_18": false, "subreddit": "punk", "score": 14, "created_utc": 1428357717}, {"yt_vid": "IX31tvT2Br8", "num_comments": 2, "title": "The Smith Street Band - \"I Don't Wanna Die Anymore\" Live at Little Elephant", "id": "34e7q5", "over_18": false, "subreddit": "punk", "score": 14, "created_utc": 1430398111}, {"yt_vid": "qADg7ZBWGRE", "num_comments": 0, "title": "In honor of new Refused, here's some old Refused: Coup D'\u00e9tat", "id": "34455x", "over_18": false, "subreddit": "punk", "score": 21, "created_utc": 1430192693}, {"yt_vid": "q8C3USK6U1M", "num_comments": 0, "title": "Where do you go when on dies? Pick it up Pete has the answer! MN Punk", "id": "34aff6", "over_18": false, "subreddit": "punk", "score": 0, "created_utc": 1430323775}, {"yt_vid": "vxHAvVtSQkY", "num_comments": 0, "title": "Folk Devils - Peel Session 1984", "id": "322l91", "over_18": false, "subreddit": "punk", "score": 2, "created_utc": 1428630704}, {"yt_vid": "MWlr3CZ1720", "num_comments": 7, "title": "Melt Banana - Uncontrollable Urge (Devo cover)", "id": "31tt3j", "over_18": false, "subreddit": "punk", "score": 40, "created_utc": 1428460432}, {"yt_vid": "Yj6LYmcu700", "num_comments": 1, "title": "A classic... \"Trouble if You Hide\"", "id": "346ni8", "over_18": false, "subreddit": "punk", "score": 5, "created_utc": 1430247050}, {"yt_vid": "wqnvmlGeCKk", "num_comments": 1, "title": "Husker Du - Diane 9/5/81", "id": "314kn9", "over_18": false, "subreddit": "punk", "score": 15, "created_utc": 1427930435}, {"yt_vid": "4VJ7zPoCyCA", "num_comments": 2, "title": "Butthole Surfers - Goofy's concern", "id": "33nzu1", "over_18": false, "subreddit": "punk", "score": 16, "created_utc": 1429841045}, {"yt_vid": "VcYhDgobgJg", "num_comments": 0, "title": "Gang Control - Keep The PMA [Full EP]", "id": "33zwby", "over_18": false, "subreddit": "punk", "score": 11, "created_utc": 1430109591}, {"yt_vid": "SFhxO2pn9Lw", "num_comments": 0, "title": "Pot Valiant - Loud Street", "id": "31kkx7", "over_18": false, "subreddit": "punk", "score": 1, "created_utc": 1428278171}, {"yt_vid": "oRpiFjqqwgM", "num_comments": 0, "title": "Quick live vid of my band - Punk/Groove/Metal.", "id": "322kqk", "over_18": false, "subreddit": "punk", "score": 0, "created_utc": 1428630455}, {"yt_vid": "bDbms0-89ps", "num_comments": 0, "title": "The Exploited - Attack", "id": "33s9m2", "over_18": false, "subreddit": "punk", "score": 2, "created_utc": 1429931741}, {"yt_vid": "p0TCklKVaJg", "num_comments": 0, "title": "Saw these guys in Berlin on Sunday and they were fantastic. Bishop's Green - Senseless Crime", "id": "33dng9", "over_18": false, "subreddit": "punk", "score": 3, "created_utc": 1429638994}, {"yt_vid": "7-5OKvVb9ec", "num_comments": 5, "title": "NOFX-Cokie the Clown", "id": "32cj66", "over_18": false, "subreddit": "punk", "score": 42, "created_utc": 1428858691}, {"yt_vid": "dgPAY6cWIUs", "num_comments": 1, "title": "\"Happy Easter, Asshole\" with Flee from the movie Suburbia", "id": "31k33h", "over_18": false, "subreddit": "punk", "score": 5, "created_utc": 1428268772}, {"yt_vid": "YNpPYVQf7fY", "num_comments": 0, "title": "From Ashes Rise - Hell In The Darkness", "id": "31upq9", "over_18": false, "subreddit": "punk", "score": 5, "created_utc": 1428481661}, {"yt_vid": "9khwIAOJyk4", "num_comments": 1, "title": "Fifteen - Punk Song", "id": "3421wk", "over_18": false, "subreddit": "punk", "score": 10, "created_utc": 1430158567}, {"yt_vid": "kKNx4_7tXGk", "num_comments": 1, "title": "Dropkick Murpheys - Noble", "id": "31azjo", "over_18": false, "subreddit": "punk", "score": 7, "created_utc": 1428066050}, {"yt_vid": "eEJGk8qfAgI", "num_comments": 1, "title": "Anybody miss Hank Von Helvete as much as I do?", "id": "31iqae", "over_18": false, "subreddit": "punk", "score": 1, "created_utc": 1428242626}, {"yt_vid": "CcIF7JbPGRw", "num_comments": 4, "title": "Choking Victim- Crack Rock Steady/Squattas Paradise EPs", "id": "333ugd", "over_18": false, "subreddit": "punk", "score": 10, "created_utc": 1429426681}, {"yt_vid": "x-4kgmCTV-U", "num_comments": 1, "title": "Teenage Depression - Frat Party", "id": "33oq8b", "over_18": false, "subreddit": "punk", "score": 6, "created_utc": 1429858056}, {"yt_vid": "iJMj_F5oc7U", "num_comments": 0, "title": "THE DECLINE - a punk rock symphony", "id": "312w9p", "over_18": false, "subreddit": "punk", "score": 1, "created_utc": 1427908538}, {"yt_vid": "GNRqMSosaC4", "num_comments": 0, "title": "Priceduifkes \"I.K.A.W (I Know A Wookie)\" from Belgium (2011) - [5:55]", "id": "32vi6r", "over_18": false, "subreddit": "punk", "score": 2, "created_utc": 1429234365}, {"yt_vid": "DFcwY-EU_qs", "num_comments": 1, "title": "The Germs-Lions Share", "id": "32t2ga", "over_18": false, "subreddit": "punk", "score": 20, "created_utc": 1429193853}, {"yt_vid": "7FkjOOi9wMw", "num_comments": 0, "title": "Hubble Bubble - New Promotion (weird belgian punk from the 70's)", "id": "33ysnv", "over_18": false, "subreddit": "punk", "score": 3, "created_utc": 1430087871}, {"yt_vid": "W_x5hD1cx3A", "num_comments": 5, "title": "Lagwagon - In Your Wake", "id": "31s16o", "over_18": false, "subreddit": "punk", "score": 20, "created_utc": 1428432136}, {"yt_vid": "JYslzZvboLs", "num_comments": 0, "title": "Dead on the Wire - Whiskey and Records. What are you gonna get for Record Store Day?", "id": "32wdj2", "over_18": false, "subreddit": "punk", "score": 4, "created_utc": 1429253935}, {"yt_vid": "dQmv0LwGUDQ", "num_comments": 0, "title": "Iron Reagan - Paycheck", "id": "31x1hp", "over_18": false, "subreddit": "punk", "score": 6, "created_utc": 1428525874}, {"yt_vid": "wduslvd1pKw", "num_comments": 0, "title": "SHAM 69 . . WHO KILLED JOE PUBLIC.mp4", "id": "31d7e3", "over_18": false, "subreddit": "punk", "score": 12, "created_utc": 1428103719}, {"yt_vid": "hpGA8NBt3mY", "num_comments": 1, "title": "The Saints - Orstralia", "id": "324kc0", "over_18": false, "subreddit": "punk", "score": 8, "created_utc": 1428678243}, {"yt_vid": "TA00pBdYphg", "num_comments": 0, "title": "M.O.T.O. - We Are The Rats", "id": "32wkr0", "over_18": false, "subreddit": "punk", "score": 12, "created_utc": 1429260700}, {"yt_vid": "oBKMsXMs8mc", "num_comments": 1, "title": "Anti-Nowhere League - Streets Of London", "id": "31vd3r", "over_18": false, "subreddit": "punk", "score": 25, "created_utc": 1428499690}, {"yt_vid": "MXGn4We3AbM", "num_comments": 31, "title": "80s Afterschool Special - The Day My Kid Went Punk [Full Movie]. This should hopefully warn parents of the dangers of punk rock and punk culture.", "id": "31fwj8", "over_18": false, "subreddit": "punk", "score": 168, "created_utc": 1428172014}, {"yt_vid": "DXgfyJmD-oM", "num_comments": 1, "title": "Arrogant sons of bitches - Royal Fuck Deluxe", "id": "31e7vd", "over_18": false, "subreddit": "punk", "score": 54, "created_utc": 1428126062}, {"yt_vid": "I1qp8dzWPlA", "num_comments": 7, "title": "Bangers - Too Many Dark Knights (Absolute must listen for fans of OWTH, Iron Chic, D4, etc.)", "id": "321739", "over_18": false, "subreddit": "punk", "score": 4, "created_utc": 1428607469}, {"yt_vid": "CNAkbbKycCM", "num_comments": 11, "title": "Butthole Surfers - Who Was in My Room Last Night", "id": "34gine", "over_18": false, "subreddit": "punk", "score": 106, "created_utc": 1430436198}, {"yt_vid": "ipBURvpouYY", "num_comments": 0, "title": "Novelty - Warsaw (Greater Manchester 1978)", "id": "32dxoo", "over_18": false, "subreddit": "punk", "score": 3, "created_utc": 1428884099}, {"yt_vid": "7OO1DpfRE00", "num_comments": 0, "title": "In the spirit of DIY ethic, my video I've practicing", "id": "32vuzj", "over_18": false, "subreddit": "punk", "score": 3, "created_utc": 1429241188}, {"yt_vid": "cYi7hrGB0bQ", "num_comments": 8, "title": "The Real McKenzies - Catch Me (2015)", "id": "330yzm", "over_18": false, "subreddit": "punk", "score": 20, "created_utc": 1429363223}, {"yt_vid": "h0qJu4q8yd8", "num_comments": 0, "title": "Bad Brains-Pay To Cum (Original 7\")", "id": "34c4p4", "over_18": false, "subreddit": "punk", "score": 43, "created_utc": 1430350559}, {"yt_vid": "encw5U624gg", "num_comments": 2, "title": "Bigwig - Sell out", "id": "33ydg1", "over_18": false, "subreddit": "punk", "score": 12, "created_utc": 1430080331}, {"yt_vid": "2n1Zx5eM38M", "num_comments": 0, "title": "The Stranglers - 5 Minutes", "id": "34e1ks", "over_18": false, "subreddit": "punk", "score": 9, "created_utc": 1430394443}, {"yt_vid": "j8YukutCX_s", "num_comments": 0, "title": "Damian Abraham and Danko Jones talk the future of punk/rock, new releases and more in Exclaim! TV's Chatroom", "id": "317lz4", "over_18": false, "subreddit": "punk", "score": 6, "created_utc": 1427994407}, {"yt_vid": "wRMXTvsCBwQ", "num_comments": 41, "title": "Refused - \"Elektra\" [new song]", "id": "3410k3", "over_18": false, "subreddit": "punk", "score": 134, "created_utc": 1430141484}, {"yt_vid": "eqWVAOZVcqk", "num_comments": 0, "title": "The Stupid Stupid Henchmen - Another Tough Day Of Illiteracy [Ska Punk, Crack Rock Steady]", "id": "33mots", "over_18": false, "subreddit": "punk", "score": 7, "created_utc": 1429818152}, {"yt_vid": "MZE_HiKAnHU", "num_comments": 0, "title": "Your Mother - Color Me Badd Religion", "id": "34cojo", "over_18": false, "subreddit": "punk", "score": 6, "created_utc": 1430360207}, {"yt_vid": "vK6J5sJ220A", "num_comments": 1, "title": "Wimps - Old Food (Seattle)", "id": "341a6e", "over_18": false, "subreddit": "punk", "score": 2, "created_utc": 1430146393}, {"yt_vid": "EzzOEOSfa3Q", "num_comments": 2, "title": "Wipers - Tragedy (1980)", "id": "31xr1l", "over_18": false, "subreddit": "punk", "score": 31, "created_utc": 1428537307}, {"yt_vid": "n20A_xWskDw", "num_comments": 3, "title": "New Good Riddance song/video \"Disputatio\"", "id": "31wv2y", "over_18": false, "subreddit": "punk", "score": 3, "created_utc": 1428523168}, {"yt_vid": "fNt1jWTUX88", "num_comments": 1, "title": "Conflict - Custom Rock (1986)", "id": "349bqm", "over_18": false, "subreddit": "punk", "score": 22, "created_utc": 1430299994}, {"yt_vid": "TcB3vbig9oc", "num_comments": 2, "title": "COCK SPARRER IN NYC FOR FIRST TIME IN 15 YEARS", "id": "32pj49", "over_18": false, "subreddit": "punk", "score": 13, "created_utc": 1429120399}, {"yt_vid": "MRO3lSXtQ6g", "num_comments": 0, "title": "Rivethead - Past Days (for fans of Dear Landlord, Screeching Weasel, etc)", "id": "32phn7", "over_18": false, "subreddit": "punk", "score": 3, "created_utc": 1429119801}, {"yt_vid": "TtXu_7-NVR4", "num_comments": 3, "title": "Dear Landlord - I live in hell", "id": "33d967", "over_18": false, "subreddit": "punk", "score": 45, "created_utc": 1429632870}, {"yt_vid": "ZSwhtQuz2tI", "num_comments": 0, "title": "Smut Peddlers - State of the State", "id": "33rx5i", "over_18": false, "subreddit": "punk", "score": 3, "created_utc": 1429924182}, {"yt_vid": "AE5yTEYwSX0", "num_comments": 3, "title": "Millencolin - Bring Me Home (New Song)", "id": "34dw8z", "over_18": false, "subreddit": "punk", "score": 19, "created_utc": 1430390390}, {"yt_vid": "Njc3FNvSBoQ", "num_comments": 8, "title": "The Melvins - Lexicon Devil (Cover of the Germs)", "id": "321i1d", "over_18": false, "subreddit": "punk", "score": 42, "created_utc": 1428612156}, {"yt_vid": "oIy7HcwVK3E", "num_comments": 4, "title": "Good Friday Special: So what if Jesus died on the cross? So what about the fucker, I don't give a toss!", "id": "31amsl", "over_18": false, "subreddit": "punk", "score": 5, "created_utc": 1428055429}, {"yt_vid": "nMmqk29m8h0", "num_comments": 17, "title": "Left\u00f6ver Crack - Nazi White Trash", "id": "33f8u4", "over_18": false, "subreddit": "punk", "score": 174, "created_utc": 1429665191}, {"yt_vid": "yiQfTIPL9mQ", "num_comments": 2, "title": "GRIMPLE- Up Your Ass", "id": "33zb8q", "over_18": false, "subreddit": "punk", "score": 9, "created_utc": 1430097549}, {"yt_vid": "M7SueHVQCzY", "num_comments": 0, "title": "GRAHAM LINDSEY: DRY BONES", "id": "31hqw6", "over_18": false, "subreddit": "punk", "score": 1, "created_utc": 1428209181}, {"yt_vid": "FVbVCZw5BPQ", "num_comments": 0, "title": "Iggy &amp; The Stooges - I Got A Right", "id": "33dpwe", "over_18": false, "subreddit": "punk", "score": 18, "created_utc": 1429640051}, {"yt_vid": "jXAC9jM646I", "num_comments": 0, "title": "JOHNNY THUNDERS BBC Saturday Live 24th March 1984", "id": "322hce", "over_18": false, "subreddit": "punk", "score": 3, "created_utc": 1428628754}, {"yt_vid": "iJMj_F5oc7U", "num_comments": 2, "title": "Orchestra performs NOFX's \"The Decline\"", "id": "31wkaw", "over_18": false, "subreddit": "punk", "score": 2, "created_utc": 1428518690}, {"yt_vid": "V8Q3YVMfwBg", "num_comments": 6, "title": "For all you wage slaves out there today.", "id": "31b1po", "over_18": false, "subreddit": "punk", "score": 10, "created_utc": 1428067341}, {"yt_vid": "QBmSFuqyKYA", "num_comments": 0, "title": "The Spermbirds - \"Dangers of thinking\"", "id": "31fjc2", "over_18": false, "subreddit": "punk", "score": 7, "created_utc": 1428165092}, {"yt_vid": "4hxw8QqSIvs", "num_comments": 11, "title": "Aus Rotten - Modern Day Witch Hunt [90s crust]", "id": "320dow", "over_18": false, "subreddit": "punk", "score": 78, "created_utc": 1428594974}, {"yt_vid": "7M0dIj3krcI", "num_comments": 1, "title": "Conflict- This Is the A.L.F (2:49)", "id": "329zy4", "over_18": false, "subreddit": "punk", "score": 17, "created_utc": 1428793096}, {"yt_vid": "YyxgEkyzT2I", "num_comments": 0, "title": "Nina Hagen - We Must Live In Love (Bob Marley Mashup) (Live at Olympia - 1980)", "id": "346b9c", "over_18": false, "subreddit": "punk", "score": 0, "created_utc": 1430241823}, {"yt_vid": "75zTFfF7G68", "num_comments": 2, "title": "Happy 420 straight-edgers!", "id": "33anhy", "over_18": false, "subreddit": "punk", "score": 0, "created_utc": 1429573953}, {"yt_vid": "2vP1gvfZvEs", "num_comments": 4, "title": "Single Mothers - Nice Dresses", "id": "3312xr", "over_18": false, "subreddit": "punk", "score": 23, "created_utc": 1429366005}, {"yt_vid": "w_Htb5_piU4", "num_comments": 0, "title": "Fugazi in Tokyo Pt. 1", "id": "338f4n", "over_18": false, "subreddit": "punk", "score": 5, "created_utc": 1429538288}, {"yt_vid": "XIjhzT6Cblo", "num_comments": 0, "title": "The BCASA - Ghost Dad", "id": "321oro", "over_18": false, "subreddit": "punk", "score": 3, "created_utc": 1428615088}, {"yt_vid": "PSTHMxBttlU", "num_comments": 0, "title": "Madness - Night Boat to Cairo", "id": "319bqm", "over_18": false, "subreddit": "punk", "score": 6, "created_utc": 1428022705}, {"yt_vid": "Fmebgonjj-A", "num_comments": 2, "title": "From Ashes Rise - Nightmares", "id": "32gh2h", "over_18": false, "subreddit": "punk", "score": 21, "created_utc": 1428942809}, {"yt_vid": "pNgAVT1zZ7E", "num_comments": 4, "title": "I made a short documentary about punk and hardcore music in my city, and tried to make it look like a zine. Check it out (6:17)", "id": "33yi3a", "over_18": false, "subreddit": "punk", "score": 15, "created_utc": 1430082540}, {"yt_vid": "OGqnNRLLUe4", "num_comments": 1, "title": "Posture &amp; The Grizzly - \"No Brains\" (live at Little Elephant)", "id": "31qzag", "over_18": false, "subreddit": "punk", "score": 7, "created_utc": 1428415665}, {"yt_vid": "UY_zmLeV0j4", "num_comments": 3, "title": "The Smith Street Band - \"The Arrogance of the Drunk Pedestrian\" (live at Little Elephant)", "id": "32x8xr", "over_18": false, "subreddit": "punk", "score": 57, "created_utc": 1429279103}, {"yt_vid": "ms4lejuJRyA", "num_comments": 2, "title": "Gray Matter - I am the Walrus", "id": "3443an", "over_18": false, "subreddit": "punk", "score": 9, "created_utc": 1430191681}, {"yt_vid": "_bEK0s69pcM", "num_comments": 13, "title": "Propagandhi - Note To Self", "id": "32d2it", "over_18": false, "subreddit": "punk", "score": 88, "created_utc": 1428868222}, {"yt_vid": "6QtHBidyl20", "num_comments": 3, "title": "No Cash - \"Gasoline\"", "id": "31kowp", "over_18": false, "subreddit": "punk", "score": 33, "created_utc": 1428280165}, {"yt_vid": "sIywtO0OY78", "num_comments": 1, "title": "Fugazi - Suggestion", "id": "332wdq", "over_18": false, "subreddit": "punk", "score": 22, "created_utc": 1429403164}, {"yt_vid": "iJMj_F5oc7U", "num_comments": 0, "title": "The Decline - A Punk Rock Symphony", "id": "32ptsa", "over_18": false, "subreddit": "punk", "score": 3, "created_utc": 1429125124}, {"yt_vid": "aY4pZlP6YtE", "num_comments": 13, "title": "Booze &amp; Glory - London Skinhead Crew", "id": "33q2ur", "over_18": false, "subreddit": "punk", "score": 35, "created_utc": 1429891328}, {"yt_vid": "cKcIoe47E5M", "num_comments": 2, "title": "Turbonegro - No, I'm Alpha Male", "id": "34b2xb", "over_18": false, "subreddit": "punk", "score": 17, "created_utc": 1430333946}, {"yt_vid": "Nteiixs4daQ", "num_comments": 5, "title": "Covered this Descendants song crappily on drums a while back, thoughts?", "id": "3307mw", "over_18": false, "subreddit": "punk", "score": 5, "created_utc": 1429336276}, {"yt_vid": "yELHkjCfJBo", "num_comments": 0, "title": "Verbal Abuse - Disintegration", "id": "33iew0", "over_18": false, "subreddit": "punk", "score": 5, "created_utc": 1429732017}, {"yt_vid": "hHNivx2RRFM", "num_comments": 23, "title": "AFI - Catch a Hot One", "id": "31ryw9", "over_18": false, "subreddit": "punk", "score": 60, "created_utc": 1428431220}, {"yt_vid": "tdmZ4IQLK-8", "num_comments": 0, "title": "Pluton Svea - There is Hate (Sweden, 1995)", "id": "316sbq", "over_18": false, "subreddit": "punk", "score": 1, "created_utc": 1427980564}, {"yt_vid": "ckpbZpDWRGQ", "num_comments": 0, "title": "A New Bug - Love's Demands [Garage Rock/Punk] (2013)", "id": "32vroz", "over_18": false, "subreddit": "punk", "score": 1, "created_utc": 1429239382}, {"yt_vid": "KsCZWRBRwHg", "num_comments": 1, "title": "JFA -- Beach Blanket Bong Out", "id": "33kknf", "over_18": false, "subreddit": "punk", "score": 6, "created_utc": 1429773608}, {"yt_vid": "XL0iTNRXWLU", "num_comments": 0, "title": "Bl'ast- It's in my blood", "id": "31l3w4", "over_18": false, "subreddit": "punk", "score": 8, "created_utc": 1428287737}, {"yt_vid": "8hALjMY3mCE", "num_comments": 0, "title": "Gonads-I Lost my Love To a UK Sub (1981)", "id": "32piyq", "over_18": false, "subreddit": "punk", "score": 3, "created_utc": 1429120336}, {"yt_vid": "JnsmwtUGXv4", "num_comments": 0, "title": "Mondo Generator - Turbonegro Must Be Destroyed", "id": "32xuqz", "over_18": false, "subreddit": "punk", "score": 2, "created_utc": 1429289163}, {"yt_vid": "egst19h2oxQ", "num_comments": 5, "title": "Cool Mutants are an awesome fuzz punk band from Southern Indiana with a few 7 inch and cassette releases aswell as 2 different reviews featured in Maximum Rock n Roll. They put on a live shown known across the Midwest as the wildest and the Mutants are the coolest!!", "id": "344ywu", "over_18": false, "subreddit": "punk", "score": 1, "created_utc": 1430215376}, {"yt_vid": "HF7e2rgzsrU", "num_comments": 1, "title": "A song for Baltimore", "id": "343gdd", "over_18": false, "subreddit": "punk", "score": 0, "created_utc": 1430180493}, {"yt_vid": "Cq422fDTB-c", "num_comments": 1, "title": "Redd Kross - Cover Band (Red Cross EP)", "id": "31hyrs", "over_18": false, "subreddit": "punk", "score": 3, "created_utc": 1428215210}, {"yt_vid": "phUKAey3OOY", "num_comments": 1, "title": "Monikers - Over (underrated pop-punk, ex-Discount)", "id": "32qi7k", "over_18": false, "subreddit": "punk", "score": 2, "created_utc": 1429135965}, {"yt_vid": "ZJxDPb4oOPI", "num_comments": 0, "title": "Simpletones - I Like Drugs, USA, 1979", "id": "34dlsl", "over_18": false, "subreddit": "punk", "score": 3, "created_utc": 1430381237}, {"yt_vid": "dauaaXGW5Wo", "num_comments": 0, "title": "Turbonegro - Welcome To The Garbage Dump", "id": "34b2bh", "over_18": false, "subreddit": "punk", "score": 1, "created_utc": 1430333694}, {"yt_vid": "_XDQLmkegEc", "num_comments": 4, "title": "I love watching these old videos and asking myself where these kids are today", "id": "3223zs", "over_18": false, "subreddit": "punk", "score": 14, "created_utc": 1428622113}, {"yt_vid": "E6_x9we5buM", "num_comments": 3, "title": "Refused - New Noise (The Evidence Cover Version, not The Bloody Beetroot...", "id": "32f3eu", "over_18": false, "subreddit": "punk", "score": 19, "created_utc": 1428910130}, {"yt_vid": "VWbKoKuns7k", "num_comments": 0, "title": "Anti-Flag (Chris 2) - Bring Out Your Dead (Acoustic) - 2014 performance, 2001 release.", "id": "320fag", "over_18": false, "subreddit": "punk", "score": 0, "created_utc": 1428595650}, {"yt_vid": "GAbgqfwt9oM", "num_comments": 0, "title": "Babes in Toyland - Ripe [3:32]", "id": "33lfyu", "over_18": false, "subreddit": "punk", "score": 1, "created_utc": 1429798003}, {"yt_vid": "mDzB-Eu8YeQ", "num_comments": 2, "title": "Flipper - Life", "id": "32ka9c", "over_18": false, "subreddit": "punk", "score": 27, "created_utc": 1429019890}, {"yt_vid": "h3JEkDShKoc", "num_comments": 12, "title": "Drive Like Jehu - Here Come The Rome Plows [90s mathy post-hardcore/emo]", "id": "320t49", "over_18": false, "subreddit": "punk", "score": 52, "created_utc": 1428601531}, {"yt_vid": "y6120QOlsfU", "num_comments": 2, "title": "Dropkick Murphys - Citizen CIA", "id": "312k12", "over_18": false, "subreddit": "punk", "score": 1, "created_utc": 1427904089}, {"yt_vid": "34jWhBMixsM", "num_comments": 1, "title": "Bad Reaction - Hate My Job", "id": "31b4v7", "over_18": false, "subreddit": "punk", "score": 1, "created_utc": 1428069210}, {"yt_vid": "BrVqIKOUTcI", "num_comments": 5, "title": "Dead Kennedys - Too Drunk to Fuck", "id": "31qi8s", "over_18": false, "subreddit": "punk", "score": 61, "created_utc": 1428405008}, {"yt_vid": "kAREP1HwCK0", "num_comments": 0, "title": "Hola Ghost - Django (Rancid cover)", "id": "32yegy", "over_18": false, "subreddit": "punk", "score": 7, "created_utc": 1429297945}, {"yt_vid": "NLKYngRjbQc", "num_comments": 5, "title": "Husker Du - Books about UFOs", "id": "31np6y", "over_18": false, "subreddit": "punk", "score": 67, "created_utc": 1428346548}, {"yt_vid": "wC5_u-MWfbU", "num_comments": 0, "title": "Milhouse - TL;DR [nerd-punk] [2011]", "id": "31hcoe", "over_18": false, "subreddit": "punk", "score": 4, "created_utc": 1428200202}, {"yt_vid": "PdEuhqxHKwo", "num_comments": 2, "title": "The Swellers Final US Show. April 4th, 2015 (Full Set)", "id": "323nvq", "over_18": false, "subreddit": "punk", "score": 16, "created_utc": 1428656417}, {"yt_vid": "qlANf0BbtWo", "num_comments": 2, "title": "Smoke or Fire: 'Integrity' from The Speakeasy", "id": "317lk4", "over_18": false, "subreddit": "punk", "score": 6, "created_utc": 1427994238}, {"yt_vid": "bmMTa2eKCVE", "num_comments": 0, "title": "Positive Junk - Misanthropy Premium British Skacore", "id": "31nc6x", "over_18": false, "subreddit": "punk", "score": 12, "created_utc": 1428340978}, {"yt_vid": "CwICLInIl8A", "num_comments": 1, "title": "New release from Brand New - Mene", "id": "32joys", "over_18": false, "subreddit": "punk", "score": 13, "created_utc": 1429005234}, {"yt_vid": "-lVRixzkNHM", "num_comments": 4, "title": "Dwarves - Blood Brother's Revenge", "id": "327168", "over_18": false, "subreddit": "punk", "score": 9, "created_utc": 1428722189}, {"yt_vid": "V8VfaHC9X54", "num_comments": 0, "title": "New Music Mondays - Those Things - Hideously Deformed Creature (Video 2015)", "id": "33bhbe", "over_18": false, "subreddit": "punk", "score": 1, "created_utc": 1429589063}, {"yt_vid": "bLtlzC_UQug", "num_comments": 0, "title": "The Embarrassment - Sex Drive", "id": "33outl", "over_18": false, "subreddit": "punk", "score": 3, "created_utc": 1429862039}, {"yt_vid": "zTBc_edXPmM", "num_comments": 0, "title": "America's Hardcore - Rollerworks L.A. 1983", "id": "31goyx", "over_18": false, "subreddit": "punk", "score": 1, "created_utc": 1428186716}, {"yt_vid": "JeF-O82S_-c", "num_comments": 2, "title": "The Making of Fat Mike's Punk Rock Musical", "id": "32bb35", "over_18": false, "subreddit": "punk", "score": 0, "created_utc": 1428823558}, {"yt_vid": "YsG5AGX8Jtk", "num_comments": 2, "title": "Is... is Jesse Michaels okay?", "id": "32zanb", "over_18": false, "subreddit": "punk", "score": 18, "created_utc": 1429314670}, {"yt_vid": "TfAV5DI4OSQ", "num_comments": 0, "title": "\"I Wanna Be a Girl\" - King Khan and The Shrines", "id": "34687a", "over_18": false, "subreddit": "punk", "score": 4, "created_utc": 1430240536}, {"yt_vid": "O9XfpDSVTPY", "num_comments": 0, "title": "Itchy Poopzkid - Dancing in the Sun (video from album released yesterday)", "id": "327suj", "over_18": false, "subreddit": "punk", "score": 1, "created_utc": 1428744755}, {"yt_vid": "yioQ6jgszKk", "num_comments": 3, "title": "42 Song Pop Punk Mashup", "id": "337t4x", "over_18": false, "subreddit": "punk", "score": 0, "created_utc": 1429521870}, {"yt_vid": "N9OnDRlrflg", "num_comments": 0, "title": "The Rebel Spell - Mover of Movers [3:27]", "id": "3250o5", "over_18": false, "subreddit": "punk", "score": 5, "created_utc": 1428685697}, {"yt_vid": "qI63R4Ateuw", "num_comments": 1, "title": "There is a band from Mtl once called \"The Bill Cosby Anarchists Society of America\" legally they had to change their name to \"The Bcasa\". They write songs about video games and TMNT - \"Street Fighter Alpha 3\"", "id": "33ffea", "over_18": false, "subreddit": "punk", "score": 1, "created_utc": 1429668528}, {"yt_vid": "_XwtKEsj5c0", "num_comments": 0, "title": "Hi! We're Drugs in the Carpet and this is our first music video!", "id": "32ezeg", "over_18": false, "subreddit": "punk", "score": 1, "created_utc": 1428906676}, {"yt_vid": "EWch-lkuIHE", "num_comments": 0, "title": "Tilt - Animated Corpse", "id": "32iw9t", "over_18": false, "subreddit": "punk", "score": 10, "created_utc": 1428982991}, {"yt_vid": "503sqO5RbAs", "num_comments": 0, "title": "Dedicated to all of the wannabe tough guys hardcore dancing at a New Found Glory show tonight- The Queers - See You Later Fuckface", "id": "32eoo7", "over_18": false, "subreddit": "punk", "score": 0, "created_utc": 1428899010}, {"yt_vid": "4aKdC_jyefg", "num_comments": 0, "title": "The Queers - I wanna be Happy", "id": "32b9dc", "over_18": false, "subreddit": "punk", "score": 15, "created_utc": 1428821930}, {"yt_vid": "H-UOz0e0dEk", "num_comments": 6, "title": "The Vandals Play For U.S. Troops in Iraq. (Sadr City)- From Joe Escalante's Channel.", "id": "31borh", "over_18": false, "subreddit": "punk", "score": 19, "created_utc": 1428078714}, {"yt_vid": "RIEwmY92r5s", "num_comments": 0, "title": "Chronic Sick - Man Rape Blues, 1982, USA", "id": "34dmhw", "over_18": false, "subreddit": "punk", "score": 4, "created_utc": 1430381836}, {"yt_vid": "u1BVuW3sgmg", "num_comments": 0, "title": "B\u00e9rurier Noir, Live (1983)", "id": "33u18r", "over_18": false, "subreddit": "punk", "score": 3, "created_utc": 1429981198}, {"yt_vid": "9GS0r7XHkwU", "num_comments": 1, "title": "my shitty band played a 10 minute set", "id": "34dlv7", "over_18": false, "subreddit": "punk", "score": 0, "created_utc": 1430381299}, {"yt_vid": "_cLuxu5-SIA", "num_comments": 0, "title": "Grand Tarantula - \"We're Gonna Get You High\" [San Diego punk]", "id": "32hq4i", "over_18": false, "subreddit": "punk", "score": 6, "created_utc": 1428962730}, {"yt_vid": "8RAIBbtpz8c", "num_comments": 0, "title": "Disorder - Air Raid, 1981, England", "id": "347u7p", "over_18": false, "subreddit": "punk", "score": 5, "created_utc": 1430266098}, {"yt_vid": "hks9pv06mO4", "num_comments": 11, "title": "This is my Punk/Ska/Hardcore band's first video. It's for our single/anthem \"Stay Filthy\" Can you dig it?", "id": "322eez", "over_18": false, "subreddit": "punk", "score": 27, "created_utc": 1428627287}, {"yt_vid": "yvUIV0WpgXA", "num_comments": 4, "title": "It's Christian punk but still good.", "id": "32ovxi", "over_18": false, "subreddit": "punk", "score": 0, "created_utc": 1429110146}, {"yt_vid": "tRoEdcBgH2Q", "num_comments": 3, "title": "Under The Influence: New York Hardcore", "id": "33mutc", "over_18": false, "subreddit": "punk", "score": 10, "created_utc": 1429820684}, {"yt_vid": "Ih3PSfd0HfU", "num_comments": 0, "title": "Acrylics - Mungus live on KCSB", "id": "347q25", "over_18": false, "subreddit": "punk", "score": 1, "created_utc": 1430264059}, {"yt_vid": "ofhqVLXQL4E", "num_comments": 2, "title": "The Vandals - Disproportioned Head", "id": "323as0", "over_18": false, "subreddit": "punk", "score": 16, "created_utc": 1428645378}, {"yt_vid": "iJMj_F5oc7U", "num_comments": 1, "title": "THE DECLINE - a punk rock symphony", "id": "313gw6", "over_18": false, "subreddit": "punk", "score": 12, "created_utc": 1427915461}, {"yt_vid": "JxaGx2t2VBM", "num_comments": 0, "title": "Flipper - Ever", "id": "31q01v", "over_18": false, "subreddit": "punk", "score": 1, "created_utc": 1428388460}, {"yt_vid": "s_LVjHtJee4", "num_comments": 2, "title": "Subhumans - Not Me", "id": "331r6o", "over_18": false, "subreddit": "punk", "score": 11, "created_utc": 1429380149}, {"yt_vid": "mUfyRvL95Rg", "num_comments": 0, "title": "Nausea-Here Today", "id": "34akht", "over_18": false, "subreddit": "punk", "score": 11, "created_utc": 1430326034}, {"yt_vid": "uMOCs0N3iiY", "num_comments": 0, "title": "\u25b6 Jello Biafra on San Francisco, Under the Golden Gate LIVE from Kink.com Part 1", "id": "3103fm", "over_18": false, "subreddit": "punk", "score": 3, "created_utc": 1427853440}, {"yt_vid": "6AiQCO7pkHw", "num_comments": 1, "title": "Poison Idea-Bog (off the new record)", "id": "33i06o", "over_18": false, "subreddit": "punk", "score": 7, "created_utc": 1429725600}, {"yt_vid": "mdf6dnZM0PM", "num_comments": 0, "title": "!Action Pact! - People [Punk Rock][UK, 1983]", "id": "34958p", "over_18": false, "subreddit": "punk", "score": 7, "created_utc": 1430293881}, {"yt_vid": "EWPCygYp_js", "num_comments": 0, "title": "Banquets - Eleanor, I Need a Garden", "id": "346gjn", "over_18": false, "subreddit": "punk", "score": 1, "created_utc": 1430244109}, {"yt_vid": "yLnK9PZgq48", "num_comments": 1, "title": "Million Dead - Smiling at Strangers on Trains", "id": "33s2iv", "over_18": false, "subreddit": "punk", "score": 9, "created_utc": 1429927409}, {"yt_vid": "G-MTO9gHmqY", "num_comments": 0, "title": "D.R.I. - Nursing Home Blues", "id": "34fkv9", "over_18": false, "subreddit": "punk", "score": 10, "created_utc": 1430420354}, {"yt_vid": "iO4uEpO1Ce4", "num_comments": 6, "title": "Neo Boys - Give Me The Message (1980 PDX)", "id": "31zzf8", "over_18": false, "subreddit": "punk", "score": 8, "created_utc": 1428588432}, {"yt_vid": "OOVUeGIOdNY", "num_comments": 3, "title": "If you've never heard of these guys and their robot drummer/bassist you need to check em out. Tartar Control - FULL SET", "id": "33ld4j", "over_18": false, "subreddit": "punk", "score": 14, "created_utc": 1429796565}, {"yt_vid": "dyC115R66Dk", "num_comments": 0, "title": "The Virus - Know It All", "id": "31kbsh", "over_18": false, "subreddit": "punk", "score": 1, "created_utc": 1428273241}, {"yt_vid": "1_KHWOqcuj0", "num_comments": 1, "title": "Boris The Sprinkler - (She Digs My) New Wave Records", "id": "31mbfx", "over_18": false, "subreddit": "punk", "score": 29, "created_utc": 1428321897}, {"yt_vid": "7OO1DpfRE00", "num_comments": 5, "title": "Descendents - I'm the One [Acoustic cover]", "id": "32qvkd", "over_18": false, "subreddit": "punk", "score": 15, "created_utc": 1429142410}, {"yt_vid": "TWT15bK8jOc", "num_comments": 1, "title": "Agent Orange covering Jefferson Airplane", "id": "31goiv", "over_18": false, "subreddit": "punk", "score": 12, "created_utc": 1428186482}, {"yt_vid": "d6vpYaL-V34", "num_comments": 7, "title": "Career Suicide - Cherry Beach (2008)", "id": "32h23b", "over_18": false, "subreddit": "punk", "score": 20, "created_utc": 1428952275}, {"yt_vid": "xvDuATZCY8I", "num_comments": 4, "title": "Sonic Youth - Teenage Riot", "id": "33yo6z", "over_18": false, "subreddit": "punk", "score": 11, "created_utc": 1430085627}, {"yt_vid": "aEUt4fXKdso", "num_comments": 4, "title": "Jello Biafra's eulogy for Dave Brockie / Oderus Urungus", "id": "328o38", "over_18": false, "subreddit": "punk", "score": 87, "created_utc": 1428768201}, {"yt_vid": "3jtL9DUxXuQ", "num_comments": 0, "title": "Lobby Boxer - \"Anxiety\"", "id": "31xokl", "over_18": false, "subreddit": "punk", "score": 0, "created_utc": 1428536122}, {"yt_vid": "ONHtRTPPDdM", "num_comments": 1, "title": "Good Riddance - Dry Season + Disputatio", "id": "331j8s", "over_18": false, "subreddit": "punk", "score": 3, "created_utc": 1429375718}, {"yt_vid": "GpcCMgXjsEs", "num_comments": 0, "title": "Electro Hippies -- Theme Toon", "id": "32q2ip", "over_18": false, "subreddit": "punk", "score": 6, "created_utc": 1429129007}, {"yt_vid": "b7JtD6WI72E", "num_comments": 0, "title": "The Descendents - Pervert", "id": "31xkb3", "over_18": false, "subreddit": "punk", "score": 1, "created_utc": 1428534141}, {"yt_vid": "ta10lV7ileA", "num_comments": 0, "title": "Horrorpops - Hitchcock starlet", "id": "31011m", "over_18": false, "subreddit": "punk", "score": 7, "created_utc": 1427852291}, {"yt_vid": "SycpgzVZwi0", "num_comments": 0, "title": "Vaginal Croutons-Toronto (Don't Wanna Go) [90's Montreal]", "id": "3261gh", "over_18": false, "subreddit": "punk", "score": 1, "created_utc": 1428702453}, {"yt_vid": "0WyJtEb2R58", "num_comments": 1, "title": "Frites Modern - Als Je Haar Maar Goed Zit (1984)(Dutch Hardcore Punk)", "id": "31szez", "over_18": false, "subreddit": "punk", "score": 1, "created_utc": 1428446706}, {"yt_vid": "DaE8cMt_8iU", "num_comments": 9, "title": "Death Grips - Klink (guitar part from Rise Above)", "id": "336vl8", "over_18": false, "subreddit": "punk", "score": 6, "created_utc": 1429496819}, {"yt_vid": "rZUbHZzHF18", "num_comments": 7, "title": "Title Fight - Secret Society", "id": "33vou7", "over_18": false, "subreddit": "punk", "score": 80, "created_utc": 1430013696}, {"yt_vid": "PV3kpjE_Sm0", "num_comments": 0, "title": "I feel like this song is very apt right now, Aus-Rotten - They Ignore Peaceful Protests", "id": "344grh", "over_18": false, "subreddit": "punk", "score": 8, "created_utc": 1430199907}, {"yt_vid": "wgn45wjt93g", "num_comments": 1, "title": "Meltdown - Citizen Fish", "id": "34c8j8", "over_18": false, "subreddit": "punk", "score": 7, "created_utc": 1430352398}, {"yt_vid": "X_ln8_SaNmc", "num_comments": 6, "title": "[REPOST FROM R/VIDEOS] A lot of punk music is associated with political statements, i.e. Fugazi/The Clash/Discharge/etc., but when I see stuff like this I just get pissed. What's your opinion on the \"Social Justice\" college movement?", "id": "33e4rt", "over_18": false, "subreddit": "punk", "score": 0, "created_utc": 1429646577}, {"yt_vid": "3wA4fOlCl8o", "num_comments": 0, "title": "The Upsets - Tommy Gun Heart", "id": "318qcd", "over_18": false, "subreddit": "punk", "score": 1, "created_utc": 1428012215}, {"yt_vid": "Td82zF3p0hY", "num_comments": 0, "title": "The Dickies - Walk Like an Egg (1985)", "id": "31jfxu", "over_18": false, "subreddit": "punk", "score": 1, "created_utc": 1428256832}, {"yt_vid": "9JPi91NLgg0", "num_comments": 2, "title": "Gas Rag - Beats Off (Chicago, 2014)", "id": "32top3", "over_18": false, "subreddit": "punk", "score": 9, "created_utc": 1429203815}, {"yt_vid": "H_gx1dInakM", "num_comments": 0, "title": "Saw a few schoolkids at the supermarket today, they reminded me of this Kill Your Idols song, because they were living the good old days and might not even realize it.", "id": "32sujl", "over_18": false, "subreddit": "punk", "score": 26, "created_utc": 1429189660}, {"yt_vid": "BUIaj338JoE", "num_comments": 0, "title": "White Lung - Face Down", "id": "32akqk", "over_18": false, "subreddit": "punk", "score": 38, "created_utc": 1428804836}, {"yt_vid": "JKn0E6zzTcw", "num_comments": 5, "title": "Baltimore punks seemed appropriate to post tonight. Not sure I'll sleep this evening with the constant sirens and helicopters in rotation above our heads. Made me think of this song, by the best Baltimore punk band probably ever, Double Dagger - Helicopter Lullaby", "id": "3441o4", "over_18": false, "subreddit": "punk", "score": 24, "created_utc": 1430190823}, {"yt_vid": "300Ocdx5m78", "num_comments": 0, "title": "Attitude Adjustment - American Paranoia [Crossover, 1986]", "id": "34fzbj", "over_18": false, "subreddit": "punk", "score": 4, "created_utc": 1430426832}, {"yt_vid": "m9vk9RCbO1k", "num_comments": 1, "title": "YDI - Why Die?", "id": "317y7s", "over_18": false, "subreddit": "punk", "score": 7, "created_utc": 1428000187}, {"yt_vid": "zqfFiLPNCME", "num_comments": 24, "title": "Propagandhi - Gifts: Less Talk More Rock turns 19 today!", "id": "33ltnt", "over_18": false, "subreddit": "punk", "score": 67, "created_utc": 1429804471}, {"yt_vid": "_otbK6oOlZY", "num_comments": 1, "title": "Glad to have been at this show. At 40 seconds that my hat being held up. Suicide Machines - New Girl", "id": "323nd9", "over_18": false, "subreddit": "punk", "score": 0, "created_utc": 1428655911}, {"yt_vid": "rKvog--SOOc", "num_comments": 0, "title": "Flogging Molly - The Guns Of Jericho (New song!)", "id": "31eadg", "over_18": false, "subreddit": "punk", "score": 21, "created_utc": 1428128006}, {"yt_vid": "_3YQuzSyiMg", "num_comments": 0, "title": "Atrocity Solution - The Protest Song [Crack Rock Steady]", "id": "33mogt", "over_18": false, "subreddit": "punk", "score": 1, "created_utc": 1429817988}, {"yt_vid": "uc9hx1YV5IY", "num_comments": 2, "title": "Yuppicide - American Oblivion - DIY Hardcore/Punk Xpost from /r/hardcore", "id": "32wqyw", "over_18": false, "subreddit": "punk", "score": 11, "created_utc": 1429266605}, {"yt_vid": "Q85KQ7cC2J4", "num_comments": 0, "title": "The Kriegers - Dog Eat Dog, Local punk rock band from Halifax, Nova Scotia", "id": "32pi54", "over_18": false, "subreddit": "punk", "score": 6, "created_utc": 1429120004}, {"yt_vid": "nfy5dD5JTf4", "num_comments": 1, "title": "The Casualties - Punx &amp; Skins", "id": "33032o", "over_18": false, "subreddit": "punk", "score": 4, "created_utc": 1429332771}, {"yt_vid": "IBqDnJyGNBs", "num_comments": 1, "title": "Lifetime - Turnpike Gates", "id": "315geh", "over_18": false, "subreddit": "punk", "score": 10, "created_utc": 1427945038}, {"yt_vid": "82fNG307NKQ", "num_comments": 1, "title": "The Hives - Well, Well, Well", "id": "31nivt", "over_18": false, "subreddit": "punk", "score": 37, "created_utc": 1428343828}, {"yt_vid": "00kMxJ2ATTo", "num_comments": 1, "title": "Betty Blowtorch - Love/Hate", "id": "32zeq8", "over_18": false, "subreddit": "punk", "score": 13, "created_utc": 1429317099}, {"yt_vid": "WIOsw2wK4os", "num_comments": 0, "title": "Choking Victim- 500 Channels [No Gods, No Managers]", "id": "32x94f", "over_18": false, "subreddit": "punk", "score": 8, "created_utc": 1429279196}, {"yt_vid": "jxi-EGoXZAs", "num_comments": 0, "title": "I Am Going to Kill the President of the United States of America - LeATHERM\u00d8UTH", "id": "31yl7p", "over_18": false, "subreddit": "punk", "score": 1, "created_utc": 1428552247}, {"yt_vid": "tAJYARIngtg", "num_comments": 0, "title": "Bad Brains -Banned in DC", "id": "332vwg", "over_18": false, "subreddit": "punk", "score": 4, "created_utc": 1429402862}, {"yt_vid": "MbD_KegM_mQ", "num_comments": 12, "title": "Jeff Rosenstock - You, In Weird Cities (Official Video)", "id": "3217yg", "over_18": false, "subreddit": "punk", "score": 78, "created_utc": 1428607826}, {"yt_vid": "c5EMAdnQafc", "num_comments": 4, "title": "The Interrupters - Babylon / Is it possible to rip Rancid off more than this ?", "id": "344u6o", "over_18": false, "subreddit": "punk", "score": 2, "created_utc": 1430211088}, {"yt_vid": "CYFs2CW2RKY", "num_comments": 0, "title": "SUICIDAL TENDENCIES - Possessed To Skate (Redux) OFFICIAL HD", "id": "33iol1", "over_18": false, "subreddit": "punk", "score": 1, "created_utc": 1429736256}, {"yt_vid": "OBFRekoeQE8", "num_comments": 6, "title": "Turbonegro - Must Be Destroyed", "id": "32tqd8", "over_18": false, "subreddit": "punk", "score": 67, "created_utc": 1429204551}, {"yt_vid": "hv4VmtwTLZc", "num_comments": 0, "title": "MY TEACHER STUDENT RELATIONSHIP LOVE STORY", "id": "31zsyc", "over_18": false, "subreddit": "punk", "score": 1, "created_utc": 1428585192}, {"yt_vid": "Krv017YFKU0", "num_comments": 20, "title": "HorrorPops - Where They Wander", "id": "32npry", "over_18": false, "subreddit": "punk", "score": 38, "created_utc": 1429079849}, {"yt_vid": "fi3khErarlM", "num_comments": 1, "title": "SPORTS - Tiny Planets", "id": "327fis", "over_18": false, "subreddit": "punk", "score": 3, "created_utc": 1428731922}, {"yt_vid": "whyWT3U8svM", "num_comments": 1, "title": "\"Sunday Night Disorientation\" by Strike Under", "id": "33olf4", "over_18": false, "subreddit": "punk", "score": 4, "created_utc": 1429854241}, {"yt_vid": "kARE0ikFYHc", "num_comments": 0, "title": "Cop on Fire - Creer En Nada [3:13]", "id": "324qrl", "over_18": false, "subreddit": "punk", "score": 4, "created_utc": 1428681229}, {"yt_vid": "aF2N8ybh2Ao", "num_comments": 0, "title": "Fiction Reform - Small Silhouette", "id": "33d4r1", "over_18": false, "subreddit": "punk", "score": 5, "created_utc": 1429630907}, {"yt_vid": "cr3I4Q6JvYQ", "num_comments": 0, "title": "Wrangler Brutes - Unmentionables - [2:10]", "id": "3387r2", "over_18": false, "subreddit": "punk", "score": 0, "created_utc": 1429534004}, {"yt_vid": "6qEXz7DGcG4", "num_comments": 11, "title": "Apparently not everyone's a fan of Choking Victim...", "id": "3141bc", "over_18": false, "subreddit": "punk", "score": 0, "created_utc": 1427922954}, {"yt_vid": "2xKFuVeBXMw", "num_comments": 0, "title": "IRON REAGAN - I Won't Go", "id": "34bjki", "over_18": false, "subreddit": "punk", "score": 7, "created_utc": 1430341131}, {"yt_vid": "A9ARqQxWh14", "num_comments": 3, "title": "Cobra Skulls - Rebel Fate [punk, Reno, Nevada, 2009]", "id": "33cin5", "over_18": false, "subreddit": "punk", "score": 39, "created_utc": 1429619428}, {"yt_vid": "iNTMgvJ7Y3g", "num_comments": 3, "title": "Titus Andronicus - No Future Part Three Escape From No Future (live Halifax Pop Explosion HD). Goddamn I love this band.", "id": "32gdo7", "over_18": false, "subreddit": "punk", "score": 38, "created_utc": 1428941283}, {"yt_vid": "2TaRnUKgr9g", "num_comments": 0, "title": "NEW Against Me! Video - Two Coffins", "id": "33e1d5", "over_18": false, "subreddit": "punk", "score": 13, "created_utc": 1429645126}, {"yt_vid": "QwsDdKH0ZQw", "num_comments": 0, "title": "The Browns - American Werewolf in Calgary", "id": "33epzm", "over_18": false, "subreddit": "punk", "score": 5, "created_utc": 1429655926}, {"yt_vid": "H3a5cTeU_Ts", "num_comments": 0, "title": "I haven't heard songs as catchy as this band in years...Plus their videos are always sick...They just released this one. Dirty Fences - Judy Don't Go [Power Punk] [2015]", "id": "33f8xr", "over_18": false, "subreddit": "punk", "score": 2, "created_utc": 1429665243}, {"yt_vid": "BsMms30YHbo", "num_comments": 0, "title": "Ripcordz - The Fence", "id": "34d7bz", "over_18": false, "subreddit": "punk", "score": 5, "created_utc": 1430370521}, {"yt_vid": "tlIb5jAEpgA", "num_comments": 0, "title": "Bouncing Souls Hopeless Romantic + Full Album", "id": "33kcxa", "over_18": false, "subreddit": "punk", "score": 22, "created_utc": 1429767403}, {"yt_vid": "vr0u4pfzLJo", "num_comments": 3, "title": "Moscow Death Brigade - Hoods Up [EP]", "id": "328lca", "over_18": false, "subreddit": "punk", "score": 3, "created_utc": 1428766659}, {"yt_vid": "rfuVLSsYOj0", "num_comments": 0, "title": "Banquets - Lyndon B. Magic Johnson", "id": "346gy1", "over_18": false, "subreddit": "punk", "score": 3, "created_utc": 1430244278}, {"yt_vid": "5Rwqf1wIvEw", "num_comments": 0, "title": "Philly Punkabilly Orchestra, Mercury Radio Theater-Minimum wage", "id": "33cplr", "over_18": false, "subreddit": "punk", "score": 6, "created_utc": 1429623646}, {"yt_vid": "Z9_n0l55b0s", "num_comments": 1, "title": "It has been 10 months since someone has posted a sloppy seconds thread. Any new kids looking for some excellent tunes listen to this asap.", "id": "33w594", "over_18": false, "subreddit": "punk", "score": 5, "created_utc": 1430024509}, {"yt_vid": "L0Yvd0Orhdg", "num_comments": 0, "title": "NICK CAVE &amp; THE CAVEMEN John Peel 28th March 1984", "id": "322lnt", "over_18": false, "subreddit": "punk", "score": 1, "created_utc": 1428630926}, {"yt_vid": "M-Lqi9YSleg", "num_comments": 0, "title": "If you guys would take a listen to this we would appreciate it very much.", "id": "31yy7m", "over_18": false, "subreddit": "punk", "score": 0, "created_utc": 1428560642}, {"yt_vid": "8S_lAB2WpTE", "num_comments": 18, "title": "Bad Religion - Infected - David Letterman (1994)", "id": "32q0ef", "over_18": false, "subreddit": "punk", "score": 120, "created_utc": 1429128087}, {"yt_vid": "Te2K_F30Gqc", "num_comments": 2, "title": "American Steel - American Steel [1998, FULL ALBUM] (New Disorder Records) Turn this shit up to an obscene volume.", "id": "317l08", "over_18": false, "subreddit": "punk", "score": 9, "created_utc": 1427994009}, {"yt_vid": "7GSM2pMAb2A", "num_comments": 2, "title": "The Adicts- You're All Fools", "id": "313but", "over_18": false, "subreddit": "punk", "score": 65, "created_utc": 1427913693}, {"yt_vid": "N1V8WiExVmE", "num_comments": 0, "title": "Krill - Torturer SXSW 2015 LIVE VIDEO", "id": "34eu1h", "over_18": false, "subreddit": "punk", "score": 4, "created_utc": 1430408749}, {"yt_vid": "4GzUh4PJVx8", "num_comments": 0, "title": "Discharge - Free Speech for the Dumb", "id": "31gomm", "over_18": false, "subreddit": "punk", "score": 17, "created_utc": 1428186547}, {"yt_vid": "PbiZMASONk0", "num_comments": 6, "title": "My ska-punk band just released a music video! It would be great if you checked it out! Turtle Power - Up All Night", "id": "32w4r4", "over_18": false, "subreddit": "punk", "score": 25, "created_utc": 1429247249}, {"yt_vid": "MNiYrKyERv0", "num_comments": 0, "title": "No pride - Green Day", "id": "33jxns", "over_18": false, "subreddit": "punk", "score": 14, "created_utc": 1429758046}, {"yt_vid": "7Eintx8HETI", "num_comments": 1, "title": "Stop The City 1984", "id": "322eka", "over_18": false, "subreddit": "punk", "score": 3, "created_utc": 1428627363}, {"yt_vid": "pGewwjlRtsw", "num_comments": 5, "title": "FEAR- \"The Mouth Don't Stop\" from More Beer, 1985", "id": "31s8cb", "over_18": false, "subreddit": "punk", "score": 22, "created_utc": 1428435114}, {"yt_vid": "UGfeLCP9SzE", "num_comments": 1, "title": "Fuzz (Ty Segall) -- Sleigh Ride, El Rey, Los Angeles [garage, punk]", "id": "341q8v", "over_18": false, "subreddit": "punk", "score": 15, "created_utc": 1430153577}, {"yt_vid": "GGQ6MYksnYw", "num_comments": 1, "title": "The Faction - Tongue Like A Battering Ram [Skate Punk, 1985]", "id": "344p39", "over_18": false, "subreddit": "punk", "score": 9, "created_utc": 1430206526}, {"yt_vid": "hqCi4gbhJ5o", "num_comments": 1, "title": "Punk Rock Is a Full Time Job", "id": "3244kj", "over_18": false, "subreddit": "punk", "score": 14, "created_utc": 1428670000}, {"yt_vid": "lUyEBQO_EGk", "num_comments": 6, "title": "saw a crusty on the street with a guitar. asked him if he knew any Choking Victim - gave him 10 dollars when he started playing this", "id": "32urkr", "over_18": false, "subreddit": "punk", "score": 20, "created_utc": 1429220887}, {"yt_vid": "xXDiJYMdfKU", "num_comments": 1, "title": "Screeching Weasel - What We Hate", "id": "328uwn", "over_18": false, "subreddit": "punk", "score": 40, "created_utc": 1428771811}, {"yt_vid": "euTMEIqTTfk", "num_comments": 0, "title": "NoMeansNo - Live in Copenhagen, 2013", "id": "321qv1", "over_18": false, "subreddit": "punk", "score": 5, "created_utc": 1428616035}, {"yt_vid": "30FOqq_5drg", "num_comments": 2, "title": "Ghoul - Dance and Fight [Hardcore][Japan, 1984]", "id": "33wid6", "over_18": false, "subreddit": "punk", "score": 6, "created_utc": 1430036402}, {"yt_vid": "Yl4J1fjuKdg", "num_comments": 0, "title": "Me and my band are working on an album, and decided to do a cover of this. I'll post the cover when we are finished!", "id": "342znx", "over_18": false, "subreddit": "punk", "score": 1, "created_utc": 1430172853}, {"yt_vid": "uv35_NLl1o4", "num_comments": 7, "title": "Kortatu- Mierda de ciudad -- Great Basque punk band", "id": "31r2iz", "over_18": false, "subreddit": "punk", "score": 20, "created_utc": 1428417227}, {"yt_vid": "_OlFex4YNIQ", "num_comments": 1, "title": "The Suspects - Riot", "id": "320dq1", "over_18": false, "subreddit": "punk", "score": 0, "created_utc": 1428594989}, {"yt_vid": "MMFc7A6NED4", "num_comments": 0, "title": "new band from cleveland hardcore punk 2015", "id": "31w204", "over_18": false, "subreddit": "punk", "score": 1, "created_utc": 1428510934}, {"yt_vid": "apuLs_ayKRM", "num_comments": 1, "title": "Fugazi - Shut The Door", "id": "33644h", "over_18": false, "subreddit": "punk", "score": 125, "created_utc": 1429481923}, {"yt_vid": "ceDDdBJqj8s", "num_comments": 1, "title": "GG Allin - Carnival Of Excess DVD- full trailer", "id": "31qsxh", "over_18": false, "subreddit": "punk", "score": 3, "created_utc": 1428412348}, {"yt_vid": "12kcpP-8jfM", "num_comments": 15, "title": "Bad Religion- American Jesus. Happy Easter /r/punk!", "id": "31j4nf", "over_18": false, "subreddit": "punk", "score": 186, "created_utc": 1428250987}, {"yt_vid": "VTbiAuqewBA", "num_comments": 0, "title": "[Punk rock, Vancouver, 2012] White Lung - \"Bag\"", "id": "33gfov", "over_18": false, "subreddit": "punk", "score": 6, "created_utc": 1429693590}, {"yt_vid": "TKYALsp-sIg", "num_comments": 0, "title": "There's only one motherfucker on Earth that's Iggy Pop, may he ever be one with the weirdness", "id": "33erd2", "over_18": false, "subreddit": "punk", "score": 1, "created_utc": 1429656573}, {"yt_vid": "Xyxx0v3B5xA", "num_comments": 17, "title": "Douchebag calls Punk \"Faggot in Red Pants\" and Sucker Punches Punk...Punk knows how to box [Potato quality, still BA though]", "id": "31nhv2", "over_18": false, "subreddit": "punk", "score": 34, "created_utc": 1428343396}, {"yt_vid": "GRctpzWM6lQ", "num_comments": 2, "title": "Wrote this with my band as an angsty 14 year old.", "id": "33fl78", "over_18": false, "subreddit": "punk", "score": 3, "created_utc": 1429671509}, {"yt_vid": "YyGizgIUNJk", "num_comments": 0, "title": "Sin Dios -- 1936", "id": "344pnx", "over_18": false, "subreddit": "punk", "score": 6, "created_utc": 1430207035}, {"yt_vid": "PEMI_tn5PQU", "num_comments": 6, "title": "Bad Religion encore - Fuck Armageddon... This Is Hell! (3/7 San Antonio, TX)", "id": "31xozk", "over_18": false, "subreddit": "punk", "score": 26, "created_utc": 1428536324}, {"yt_vid": "TU1Z8QApbkM", "num_comments": 0, "title": "SNFU - Bumper Stickers", "id": "32yrpv", "over_18": false, "subreddit": "punk", "score": 5, "created_utc": 1429304202}, {"yt_vid": "_ioHvKCn_wE", "num_comments": 5, "title": "Mark Atkins chucks a chair at his drummer when a prank goes wrong.", "id": "3249fv", "over_18": false, "subreddit": "punk", "score": 7, "created_utc": 1428672794}, {"yt_vid": "dzRGmuL5o4M", "num_comments": 2, "title": "The Menzingers - \"Where Your Heartache Exists\"", "id": "33jv40", "over_18": false, "subreddit": "punk", "score": 31, "created_utc": 1429756692}, {"yt_vid": "jxq6S9mWQEA", "num_comments": 1, "title": "Tartar Control - Smoking Crack", "id": "33ro9i", "over_18": false, "subreddit": "punk", "score": 17, "created_utc": 1429918948}, {"yt_vid": "7hFgEV9koyc", "num_comments": 0, "title": "X-motel room in my bed", "id": "34ba8o", "over_18": false, "subreddit": "punk", "score": 2, "created_utc": 1430337098}, {"yt_vid": "m3cnPLahYwE", "num_comments": 60, "title": "Any love for A Wilhelm Scream?", "id": "315lc5", "over_18": false, "subreddit": "punk", "score": 106, "created_utc": 1427947625}, {"yt_vid": "72IzhvflvV0", "num_comments": 3, "title": "My Social Distortion Tribute - 8 covers. Let me know how much it sucks. haha", "id": "32w5g7", "over_18": false, "subreddit": "punk", "score": 8, "created_utc": 1429247705}, {"yt_vid": "jxw6rTCY8Yk", "num_comments": 0, "title": "G.G. Allin - Hard Candy Cock", "id": "339hdu", "over_18": false, "subreddit": "punk", "score": 0, "created_utc": 1429555413}, {"yt_vid": "5Lh9kx5qYy8", "num_comments": 1, "title": "The Joykiller - Tonight [2015]", "id": "321cq0", "over_18": false, "subreddit": "punk", "score": 2, "created_utc": 1428609866}, {"yt_vid": "0dX6LL7b8Y0", "num_comments": 21, "title": "New TITUS ANDRONICUS - \"DIMED OUT\"", "id": "34ejky", "over_18": false, "subreddit": "punk", "score": 86, "created_utc": 1430404118}, {"yt_vid": "OLWlF0lF9IQ", "num_comments": 0, "title": "Pinact - Anxiety (Live) - new Scottish punk band", "id": "31or3x", "over_18": false, "subreddit": "punk", "score": 3, "created_utc": 1428363359}, {"yt_vid": "SltdhNFBhIg", "num_comments": 0, "title": "No Apparent Reason - Dogs - Music Video (Switzerland, 2015)", "id": "32hhg8", "over_18": false, "subreddit": "punk", "score": 4, "created_utc": 1428958859}, {"yt_vid": "LYmoDjxcBrA", "num_comments": 49, "title": "Death Grips - Beyond Alive", "id": "33s5tt", "over_18": false, "subreddit": "punk", "score": 39, "created_utc": 1429929419}, {"yt_vid": "zVMtZldTqoc", "num_comments": 1, "title": "Cockney Rejects - The Rocker [Oi!, 1980]", "id": "34ccry", "over_18": false, "subreddit": "punk", "score": 16, "created_utc": 1430354466}, {"yt_vid": "Yb4tG4Zg7Rs", "num_comments": 0, "title": "NON SERVIUM - ACAB feat. EVARISTO", "id": "33qp2c", "over_18": false, "subreddit": "punk", "score": 1, "created_utc": 1429901279}, {"yt_vid": "lvMMn8gj0kQ", "num_comments": 0, "title": "H\u00dcSKER D\u00dc - \"The Children's Crusade\" '81-Bootleg", "id": "31a6wp", "over_18": false, "subreddit": "punk", "score": 4, "created_utc": 1428040755}, {"yt_vid": "hY2tv30d9RE", "num_comments": 34, "title": "Dinosaur Jr. - \"How'd You Pin That One on Me\" (Punk song by a non-punk band)", "id": "328m2l", "over_18": false, "subreddit": "punk", "score": 36, "created_utc": 1428767101}, {"yt_vid": "tft3GSCvbAg", "num_comments": 0, "title": "Awaria- G\u0142og\u00f3w", "id": "311nbm", "over_18": false, "subreddit": "punk", "score": 1, "created_utc": 1427888914}, {"yt_vid": "paJqtWl5GDw", "num_comments": 1, "title": "The saxophonist from X Ray Spex's side project was pretty cool.....Essential Logic - Quality Crayon Wax O.K [Post Punk, 1979]", "id": "340cko", "over_18": false, "subreddit": "punk", "score": 3, "created_utc": 1430122484}, {"yt_vid": "Y-cj-r5bSP8", "num_comments": 1, "title": "Svetlanas - 147 Voices", "id": "328pzy", "over_18": false, "subreddit": "punk", "score": 4, "created_utc": 1428769202}, {"yt_vid": "l7AFxifwlFA", "num_comments": 0, "title": "Nudes - Sick Fucker (2012) [2:24]", "id": "34dori", "over_18": false, "subreddit": "punk", "score": 3, "created_utc": 1430383844}, {"yt_vid": "7WnzrpX_roY", "num_comments": 1, "title": "Cunter- 27 (Full Album)", "id": "331bnu", "over_18": false, "subreddit": "punk", "score": 3, "created_utc": 1429371556}, {"yt_vid": "eNNsQsbyS5Q", "num_comments": 1, "title": "Knuckledust - Dust to Dust", "id": "31gqma", "over_18": false, "subreddit": "punk", "score": 1, "created_utc": 1428187612}, {"yt_vid": "Rnku5W5QZfs", "num_comments": 0, "title": "The Adicts - Fuck it Up", "id": "32a8zl", "over_18": false, "subreddit": "punk", "score": 1, "created_utc": 1428798173}, {"yt_vid": "d8PQTRBgpyI", "num_comments": 2, "title": "Punk is alive and well. Nunhex-Miami-04/11/15", "id": "32jb8l", "over_18": false, "subreddit": "punk", "score": 0, "created_utc": 1428992930}, {"yt_vid": "oqdQ-YZxva0", "num_comments": 0, "title": "Most Precious Blood - Rise above - YouTube", "id": "3354in", "over_18": false, "subreddit": "punk", "score": 8, "created_utc": 1429463877}, {"yt_vid": "VFnnSqCHqso", "num_comments": 0, "title": "Wonk Unit - Je M'appelle Alex", "id": "342ckj", "over_18": false, "subreddit": "punk", "score": 4, "created_utc": 1430162961}, {"yt_vid": "nkXOTkahRQs", "num_comments": 0, "title": "Suicide File - I Hate You", "id": "34e895", "over_18": false, "subreddit": "punk", "score": 8, "created_utc": 1430398427}, {"yt_vid": "5ydz52zcAoo", "num_comments": 7, "title": "NAAMAHK - 2014 Demo Cassette", "id": "33ge61", "over_18": false, "subreddit": "punk", "score": 2, "created_utc": 1429692139}, {"yt_vid": "GXJWdSmVy_g", "num_comments": 0, "title": "This New Hampshire pirate punk band has been playing since the 70's and really deserves some recognition. The Jonee Earthquake Band - \"DIY or Die\"", "id": "33eak7", "over_18": false, "subreddit": "punk", "score": 2, "created_utc": 1429649056}, {"yt_vid": "ba8VLnv-g4s", "num_comments": 2, "title": "Against All Authority- Nothing New For Trash Like You (full album)", "id": "32x9pl", "over_18": false, "subreddit": "punk", "score": 47, "created_utc": 1429279479}, {"yt_vid": "fQ2XXWBb1Vg", "num_comments": 0, "title": "Refused - Rather Be Dead (Bielefeld 1998 - Master)", "id": "31x1mb", "over_18": false, "subreddit": "punk", "score": 14, "created_utc": 1428525931}, {"yt_vid": "Mr5R5Wof81k", "num_comments": 3, "title": "Deviates - My Life (FULL ALBUM) 33:08", "id": "349wuz", "over_18": false, "subreddit": "punk", "score": 3, "created_utc": 1430314935}, {"yt_vid": "OGA9SGDdEag", "num_comments": 2, "title": "Teenage Bottlerocket - I Wanna Die", "id": "31cq6y", "over_18": false, "subreddit": "punk", "score": 30, "created_utc": 1428095125}, {"yt_vid": "ylayCDTZAMk", "num_comments": 0, "title": "Crippled Youth - Positive Scene", "id": "34d13k", "over_18": false, "subreddit": "punk", "score": 3, "created_utc": 1430366739}]